lnurl_nostr1/__init__.py
lnurl_nostr1/cli.py
lnurl_nostr1/core.py
lnurl_nostr1/exceptions.py
lnurl_nostr1/helpers.py
lnurl_nostr1/models.py
lnurl_nostr1/py.typed/py.typed
lnurl_nostr1/types.py
lnurl_nostr1-0.5.1rc3.dist-info/LICENSE
lnurl_nostr1-0.5.1rc3.dist-info/METADATA
lnurl_nostr1-0.5.1rc3.dist-info/WHEEL
lnurl_nostr1-0.5.1rc3.dist-info/entry_points.txt
lnurl_nostr1-0.5.1rc3.dist-info/RECORD
