Metadata-Version: 2.1
Name: lnurl_nostr1
Version: 0.5.1rc3
Summary: LNURL implementation for Python, with support for future nostr1 protocol.
License: MIT
Author: Alan Bits
Author-email: alan@lnbits.com
Requires-Python: >=3.9,<4.0
Classifier: License :: OSI Approved :: MIT License
Classifier: Programming Language :: Python :: 3
Classifier: Programming Language :: Python :: 3.9
Classifier: Programming Language :: Python :: 3.10
Classifier: Programming Language :: Python :: 3.11
Classifier: Programming Language :: Python :: 3.12
Requires-Dist: bech32 (>=1.2.0,<2.0.0)
Requires-Dist: bolt11 (>=2.0.5,<3.0.0)
Requires-Dist: ecdsa (>=0.19.0,<0.20.0)
Requires-Dist: httpx (>=0.27.0,<0.28.0)
Requires-Dist: pydantic (>=1,<2)
